scicrypt/__init__.py
scicrypt/_basic.py
scicrypt/basic.py
scicrypt/version.py
scicrypt-0.6.dist-info/METADATA
scicrypt-0.6.dist-info/WHEEL
scicrypt-0.6.dist-info/top_level.txt
scicrypt-0.6.dist-info/RECORD
